collective.bbcodesnippets-1.0.0-py3.9-nspkg.pth
collective/bbcodesnippets/__init__.py
collective/bbcodesnippets/configure.zcml
collective/bbcodesnippets/controlpanel.py
collective/bbcodesnippets/demo.pt
collective/bbcodesnippets/demo.py
collective/bbcodesnippets/formatters.py
collective/bbcodesnippets/formatters.zcml
collective/bbcodesnippets/indexer.py
collective/bbcodesnippets/interfaces.py
collective/bbcodesnippets/menu.py
collective/bbcodesnippets/parser.py
collective/bbcodesnippets/restapi.py
collective/bbcodesnippets/setuphandlers.py
collective/bbcodesnippets/testing.py
collective/bbcodesnippets/tinymce.py
collective/bbcodesnippets/transform.py
collective/bbcodesnippets/profiles/default/browserlayer.xml
collective/bbcodesnippets/profiles/default/catalog.xml
collective/bbcodesnippets/profiles/default/controlpanel.xml
collective/bbcodesnippets/profiles/default/metadata.xml
collective/bbcodesnippets/profiles/default/registry.xml
collective/bbcodesnippets/profiles/uninstall/browserlayer.xml
collective/bbcodesnippets/profiles/uninstall/controlpanel.xml
collective/bbcodesnippets/profiles/uninstall/registry.xml
collective/bbcodesnippets/static/bbcodeicon.png
collective/bbcodesnippets/static/bbcodeicon.svg
collective/bbcodesnippets/static/collective.bbcodesnippets.js
collective/bbcodesnippets/static/collective.bbcodesnippets.js.map
collective/bbcodesnippets/static/collective.bbcodesnippets.min.js
collective/bbcodesnippets/static/collective.bookmarks.css
collective/bbcodesnippets/static/collective.bookmarks.css.map
collective/bbcodesnippets/tests/__init__.py
collective/bbcodesnippets/tests/mocks.py
collective/bbcodesnippets/tests/test_parser.py
collective/bbcodesnippets/tests/test_setup.py
collective/bbcodesnippets/tests/test_transform.py
collective.bbcodesnippets-1.0.0.dist-info/LICENSE.rst
collective.bbcodesnippets-1.0.0.dist-info/METADATA
collective.bbcodesnippets-1.0.0.dist-info/WHEEL
collective.bbcodesnippets-1.0.0.dist-info/entry_points.txt
collective.bbcodesnippets-1.0.0.dist-info/namespace_packages.txt
collective.bbcodesnippets-1.0.0.dist-info/top_level.txt
collective.bbcodesnippets-1.0.0.dist-info/RECORD
