Metadata-Version: 2.1
Name: collective.bbcodesnippets
Version: 1.0.0
Summary: Add BBCode in the site and transform it.
Home-page: https://github.com/collective/collective.bbcodesnippets
Author: BlueDynamics Alliance
Author-email: dev@bluedynamics.com
License: BSD
Keywords: zope plone bbcode
Platform: UNKNOWN
Classifier: Environment :: Web Environment
Classifier: Framework :: Plone
Classifier: Framework :: Plone :: Addon
Classifier: Framework :: Plone :: 5.2
Classifier: Framework :: Zope
Classifier: Framework :: Zope :: 4
Classifier: Framework :: Zope :: 5
Classifier: License :: OSI Approved :: GNU General Public License (GPL)
Classifier: Operating System :: OS Independent
Classifier: Programming Language :: Python
Classifier: Programming Language :: Python :: 2.7
Classifier: Programming Language :: Python :: 3.7
Classifier: Programming Language :: Python :: 3.8
Classifier: Topic :: Internet :: WWW/HTTP :: Dynamic Content
Classifier: Development Status :: 3 - Alpha
Requires-Dist: bbcode (>=1.1)
Requires-Dist: setuptools (>=39.1.0)
Requires-Dist: Products.CMFPlone (>=5.2)
Requires-Dist: plone.restapi
Provides-Extra: test
Requires-Dist: plone.app.testing ; extra == 'test'
Requires-Dist: plone.app.robotframework ; extra == 'test'
Requires-Dist: mock ; (python_version < "3") and extra == 'test'
